cadquery_ocp/LICENSE
cadquery_ocp-7.8.1.1.post1.dist-info/RECORD
cadquery_ocp-7.8.1.1.post1.dist-info/WHEEL
cadquery_ocp-7.8.1.1.post1.dist-info/top_level.txt
cadquery_ocp-7.8.1.1.post1.dist-info/METADATA
OCP/__init__.py
OCP/OCP.cpython-313-darwin.so
OCP/FilletSurf/__init__.py
OCP/ExprIntrp/__init__.py
OCP/InterfaceGraphic/__init__.py
OCP/ChFi3d/__init__.py
OCP/FairCurve/__init__.py
OCP/StepAP209/__init__.py
OCP/Draft/__init__.py
OCP/RWStepVisual/__init__.py
OCP/IGESDraw/__init__.py
OCP/TopCnx/__init__.py
OCP/TopoDS/__init__.py
OCP/HLRAppli/__init__.py
OCP/XCAFView/__init__.py
OCP/BSplCLib/__init__.py
OCP/CDM/__init__.py
OCP/IGESGraph/__init__.py
OCP/IGESDefs/__init__.py
OCP/CPnts/__init__.py
OCP/BiTgte/__init__.py
OCP/XmlLDrivers/__init__.py
OCP/HatchGen/__init__.py
OCP/IVtkVTK/__init__.py
OCP/Interface/__init__.py
OCP/IVtk/__init__.py
OCP/HLRBRep/__init__.py
OCP/IGESConvGeom/__init__.py
OCP/BinTools/__init__.py
OCP/MAT/__init__.py
OCP/RWStepShape/__init__.py
OCP/BOPAlgo/__init__.py
OCP/RWStepDimTol/__init__.py
OCP/GeomEvaluator/__init__.py
OCP/IGESSolid/__init__.py
OCP/TopOpeBRep/__init__.py
OCP/FEmTool/__init__.py
OCP/STEPCAFControl/__init__.py
OCP/DsgPrs/__init__.py
OCP/IGESToBRep/__init__.py
OCP/Adaptor3d/__init__.py
OCP/IGESSelect/__init__.py
OCP/IntRes2d/__init__.py
OCP/StlAPI/__init__.py
OCP/RWStepAP242/__init__.py
OCP/STEPSelections/__init__.py
OCP/TopLoc/__init__.py
OCP/HLRAlgo/__init__.py
OCP/ChFiDS/__init__.py
OCP/PrsMgr/__init__.py
OCP/MMgt/__init__.py
OCP/Geom2d/__init__.py
OCP/IntImpParGen/__init__.py
OCP/IGESBasic/__init__.py
OCP/LDOM/__init__.py
OCP/AppParCurves/__init__.py
OCP/StdPrs/__init__.py
OCP/BinLDrivers/__init__.py
OCP/ShapeBuild/__init__.py
OCP/XmlMFunction/__init__.py
OCP/BRepLProp/__init__.py
OCP/IGESCAFControl/__init__.py
OCP/Vrml/__init__.py
OCP/GeomToIGES/__init__.py
OCP/GeomPlate/__init__.py
OCP/IGESDimen/__init__.py
OCP/BRepOffset/__init__.py
OCP/GeomLProp/__init__.py
OCP/TColGeom/__init__.py
OCP/IntStart/__init__.py
OCP/StdDrivers/__init__.py
OCP/IntCurve/__init__.py
OCP/IGESData/__init__.py
OCP/BlendFunc/__init__.py
OCP/OSD/__init__.py
