Metadata-Version: 2.2
Name: cadquery-ocp
Version: 7.8.1.1.post1
Summary: Python wrapper for Open CASCADE Technology 3D geometry library based on the official CadQuery/OCP sources
Author: Bernhard Walter
Requires-Python: <3.14,>=3.10
Requires-Dist: cadquery_vtk==9.3.1
